voter_if.v
module voter_if (I, O);
input [3:0] I; 
output [3:1] O; 
reg [3:1] O;  

always @(I) begin
    case (I)    
     4'b0000 : O = 3'b100;  
     4'b0001 : O = 3'b100;  
     4'b0010 : O = 3'b100;  
     4'b0011 : O = 3'b010;  
     4'b0100 : O = 3'b100;  
     4'b0101 : O = 3'b010;
     4'b0110 : O = 3'b010;
     4'b0111 : O = 3'b001;
     4'b1000 : O = 3'b100;
     4'b1001 : O = 3'b010;
     4'b1010 : O = 3'b010;
     4'b1011 : O = 3'b001;
     4'b1100 : O = 3'b010;
     4'b1101 : O = 3'b001;
     4'b1110 : O = 3'b001;
     4'b1111 : O = 3'b001;
     default: O = 3'b000;
 endcase

end

endmodule

voter_if_tb.v
`timescale 1ns/1ps 

module voter_if_tb();

reg [3:0] I_tb;
wire [3:1] O_tb;

voter_if voter4P(.I(I_tb),.O(O_tb)); 

initial begin
    #0  I_tb = 4'b0000; 
    #10 I_tb = 4'b0000; 
    #10 I_tb = 4'b0001;
    #10 I_tb = 4'b0010;
    #10 I_tb = 4'b0011;
    #10 I_tb = 4'b0100;
    #10 I_tb = 4'b0101;
    #10 I_tb = 4'b0110;
    #10 I_tb = 4'b0111;
    #10 I_tb = 4'b1000;
    #10 I_tb = 4'b1001;
    #10 I_tb = 4'b1010;
    #10 I_tb = 4'b1011;
    #10 I_tb = 4'b1100;
    #10 I_tb = 4'b1101;
    #10 I_tb = 4'b1110;
    #10 I_tb = 4'b1111;
    #10 $finish;
    end
initial
    begin
        $dumpfile("voter_if.vcd"); 
        $dumpvars(0,voter_if_tb);  
    end


endmodule

voter_if.vcd
$date
	Sat Apr 16 19:38:36 2022
$end
$version
	Icarus Verilog
$end
$timescale
	1ps
$end
$scope module voter_if_tb $end
$var wire 3 ! O_tb [3:1] $end
$var reg 4 " I_tb [3:0] $end
$scope module voter4P $end
$var wire 4 # I [3:0] $end
$var reg 3 $ O [3:1] $end
$upscope $end
$upscope $end
$enddefinitions $end
#0
$dumpvars
b100 $
b0 #
b0 "
b100 !
$end
#20000
b1 "
b1 #
#30000
b10 "
b10 #
#40000
b10 !
b10 $
b11 "
b11 #
#50000
b100 !
b100 $
b100 "
b100 #
#60000
b10 !
b10 $
b101 "
b101 #
#70000
b110 "
b110 #
#80000
b1 !
b1 $
b111 "
b111 #
#90000
b100 !
b100 $
b1000 "
b1000 #
#100000
b10 !
b10 $
b1001 "
b1001 #
#110000
b1010 "
b1010 #
#120000
b1 !
b1 $
b1011 "
b1011 #
#130000
b10 !
b10 $
b1100 "
b1100 #
#140000
b1 !
b1 $
b1101 "
b1101 #
#150000
b1110 "
b1110 #
#160000
b1111 "
b1111 #
